{
  "api/tokenholders新" : {
    "transaction" : "api/tokenholders新",
    "sampleCount" : 50,
    "errorCount" : 50,
    "errorPct" : 100.0,
    "meanResTime" : 7015.599999999998,
    "minResTime" : 7009.0,
    "maxResTime" : 7020.0,
    "pct1ResTime" : 7018.0,
    "pct2ResTime" : 7019.0,
    "pct3ResTime" : 7020.0,
    "throughput" : 0.06354144427161172,
    "receivedKBytesPerSec" : 0.1643762557377924,
    "sentKBytesPerSec" : 0.0
  },
  "api/account/list  " : {
    "transaction" : "api/account/list  ",
    "sampleCount" : 50,
    "errorCount" : 0,
    "errorPct" : 0.0,
    "meanResTime" : 69.53999999999999,
    "minResTime" : 61.0,
    "maxResTime" : 152.0,
    "pct1ResTime" : 86.5,
    "pct2ResTime" : 93.59999999999997,
    "pct3ResTime" : 152.0,
    "throughput" : 0.06410601596496222,
    "receivedKBytesPerSec" : 0.056969213406362906,
    "sentKBytesPerSec" : 0.008764494370209678
  },
  "api/account/list新" : {
    "transaction" : "api/account/list新",
    "sampleCount" : 50,
    "errorCount" : 50,
    "errorPct" : 100.0,
    "meanResTime" : 7013.499999999999,
    "minResTime" : 7009.0,
    "maxResTime" : 7018.0,
    "pct1ResTime" : 7017.0,
    "pct2ResTime" : 7018.0,
    "pct3ResTime" : 7018.0,
    "throughput" : 0.06354273630272776,
    "receivedKBytesPerSec" : 0.16437959811125571,
    "sentKBytesPerSec" : 0.0
  },
  "api/trc10trc20-transfer新" : {
    "transaction" : "api/trc10trc20-transfer新",
    "sampleCount" : 50,
    "errorCount" : 50,
    "errorPct" : 100.0,
    "meanResTime" : 7014.579999999999,
    "minResTime" : 7009.0,
    "maxResTime" : 7019.0,
    "pct1ResTime" : 7018.0,
    "pct2ResTime" : 7019.0,
    "pct3ResTime" : 7019.0,
    "throughput" : 0.06368510010660886,
    "receivedKBytesPerSec" : 0.1647478810375067,
    "sentKBytesPerSec" : 0.0
  },
  "api/token新" : {
    "transaction" : "api/token新",
    "sampleCount" : 50,
    "errorCount" : 50,
    "errorPct" : 100.0,
    "meanResTime" : 7014.819999999999,
    "minResTime" : 7009.0,
    "maxResTime" : 7020.0,
    "pct1ResTime" : 7015.9,
    "pct2ResTime" : 7017.45,
    "pct3ResTime" : 7020.0,
    "throughput" : 0.06355363990761842,
    "receivedKBytesPerSec" : 0.16440780480007933,
    "sentKBytesPerSec" : 0.0
  },
  "api/token_trc20/holders新" : {
    "transaction" : "api/token_trc20/holders新",
    "sampleCount" : 50,
    "errorCount" : 50,
    "errorPct" : 100.0,
    "meanResTime" : 7013.68,
    "minResTime" : 7009.0,
    "maxResTime" : 7019.0,
    "pct1ResTime" : 7018.9,
    "pct2ResTime" : 7019.0,
    "pct3ResTime" : 7019.0,
    "throughput" : 0.06354112127204241,
    "receivedKBytesPerSec" : 0.1643754201656644,
    "sentKBytesPerSec" : 0.0
  },
  "api/account新" : {
    "transaction" : "api/account新",
    "sampleCount" : 50,
    "errorCount" : 50,
    "errorPct" : 100.0,
    "meanResTime" : 7015.879999999999,
    "minResTime" : 7014.0,
    "maxResTime" : 7017.0,
    "pct1ResTime" : 7017.0,
    "pct2ResTime" : 7017.0,
    "pct3ResTime" : 7017.0,
    "throughput" : 0.06354289781031174,
    "receivedKBytesPerSec" : 0.1643800159174959,
    "sentKBytesPerSec" : 0.0
  },
  "api/vote/witness" : {
    "transaction" : "api/vote/witness",
    "sampleCount" : 50,
    "errorCount" : 0,
    "errorPct" : 0.0,
    "meanResTime" : 83.7,
    "minResTime" : 81.0,
    "maxResTime" : 113.0,
    "pct1ResTime" : 86.9,
    "pct2ResTime" : 97.69999999999997,
    "pct3ResTime" : 113.0,
    "throughput" : 0.06410774203557466,
    "receivedKBytesPerSec" : 3.9993715037240185,
    "sentKBytesPerSec" : 0.008764730356426224
  },
  "api/transfer新" : {
    "transaction" : "api/transfer新",
    "sampleCount" : 50,
    "errorCount" : 50,
    "errorPct" : 100.0,
    "meanResTime" : 7013.759999999999,
    "minResTime" : 7009.0,
    "maxResTime" : 7018.0,
    "pct1ResTime" : 7017.0,
    "pct2ResTime" : 7017.45,
    "pct3ResTime" : 7018.0,
    "throughput" : 0.06354814725376683,
    "receivedKBytesPerSec" : 0.16439359577659016,
    "sentKBytesPerSec" : 0.0
  },
  "api/vote/witness新" : {
    "transaction" : "api/vote/witness新",
    "sampleCount" : 50,
    "errorCount" : 50,
    "errorPct" : 100.0,
    "meanResTime" : 7014.06,
    "minResTime" : 7010.0,
    "maxResTime" : 7020.0,
    "pct1ResTime" : 7017.9,
    "pct2ResTime" : 7020.0,
    "pct3ResTime" : 7020.0,
    "throughput" : 0.06354305931871673,
    "receivedKBytesPerSec" : 0.16438043372585998,
    "sentKBytesPerSec" : 0.0
  },
  "api/trc10trc20-transfer" : {
    "transaction" : "api/trc10trc20-transfer",
    "sampleCount" : 50,
    "errorCount" : 0,
    "errorPct" : 0.0,
    "meanResTime" : 202.32000000000002,
    "minResTime" : 33.0,
    "maxResTime" : 1926.0,
    "pct1ResTime" : 580.6999999999998,
    "pct2ResTime" : 984.3999999999975,
    "pct3ResTime" : 1926.0,
    "throughput" : 0.06420990990065442,
    "receivedKBytesPerSec" : 0.5937535516106414,
    "sentKBytesPerSec" : 0.019689366903130362
  },
  "api/transfer" : {
    "transaction" : "api/transfer",
    "sampleCount" : 50,
    "errorCount" : 0,
    "errorPct" : 0.0,
    "meanResTime" : 620.4599999999999,
    "minResTime" : 545.0,
    "maxResTime" : 837.0,
    "pct1ResTime" : 722.0,
    "pct2ResTime" : 796.1999999999998,
    "pct3ResTime" : 837.0,
    "throughput" : 0.06406100657778416,
    "receivedKBytesPerSec" : 0.21131999425693077,
    "sentKBytesPerSec" : 0.008508102436111959
  },
  "api/token_trc20/transfers" : {
    "transaction" : "api/token_trc20/transfers",
    "sampleCount" : 50,
    "errorCount" : 0,
    "errorPct" : 0.0,
    "meanResTime" : 401.46000000000004,
    "minResTime" : 41.0,
    "maxResTime" : 3397.0,
    "pct1ResTime" : 1175.7999999999997,
    "pct2ResTime" : 3322.0999999999995,
    "pct3ResTime" : 3397.0,
    "throughput" : 0.06411489388985062,
    "receivedKBytesPerSec" : 0.36050352231198307,
    "sentKBytesPerSec" : 0.017280967493748797
  },
  "api/token" : {
    "transaction" : "api/token",
    "sampleCount" : 50,
    "errorCount" : 0,
    "errorPct" : 0.0,
    "meanResTime" : 35.68,
    "minResTime" : 25.0,
    "maxResTime" : 180.0,
    "pct1ResTime" : 65.89999999999998,
    "pct2ResTime" : 130.09999999999968,
    "pct3ResTime" : 180.0,
    "throughput" : 0.06411111225086422,
    "receivedKBytesPerSec" : 0.7753437637838891,
    "sentKBytesPerSec" : 0.00832693157164545
  },
  "api/asset/transfer" : {
    "transaction" : "api/asset/transfer",
    "sampleCount" : 50,
    "errorCount" : 0,
    "errorPct" : 0.0,
    "meanResTime" : 602.08,
    "minResTime" : 535.0,
    "maxResTime" : 787.0,
    "pct1ResTime" : 692.7,
    "pct2ResTime" : 736.2499999999998,
    "pct3ResTime" : 787.0,
    "throughput" : 0.0640714319580614,
    "receivedKBytesPerSec" : 0.20115801705004877,
    "sentKBytesPerSec" : 0.008884905603559297
  },
  "api/witness新" : {
    "transaction" : "api/witness新",
    "sampleCount" : 50,
    "errorCount" : 50,
    "errorPct" : 100.0,
    "meanResTime" : 7013.619999999999,
    "minResTime" : 7009.0,
    "maxResTime" : 7019.0,
    "pct1ResTime" : 7015.0,
    "pct2ResTime" : 7019.0,
    "pct3ResTime" : 7019.0,
    "throughput" : 0.06354297856441161,
    "receivedKBytesPerSec" : 0.16438022482141246,
    "sentKBytesPerSec" : 0.0
  },
  "api/token_trc20新" : {
    "transaction" : "api/token_trc20新",
    "sampleCount" : 50,
    "errorCount" : 50,
    "errorPct" : 100.0,
    "meanResTime" : 7013.319999999999,
    "minResTime" : 7009.0,
    "maxResTime" : 7015.0,
    "pct1ResTime" : 7014.0,
    "pct2ResTime" : 7015.0,
    "pct3ResTime" : 7015.0,
    "throughput" : 0.0635416865234437,
    "receivedKBytesPerSec" : 0.16437688242246326,
    "sentKBytesPerSec" : 0.0
  },
  "api/token_trc20/transfers新" : {
    "transaction" : "api/token_trc20/transfers新",
    "sampleCount" : 50,
    "errorCount" : 50,
    "errorPct" : 100.0,
    "meanResTime" : 7013.980000000001,
    "minResTime" : 7009.0,
    "maxResTime" : 7019.0,
    "pct1ResTime" : 7018.0,
    "pct2ResTime" : 7019.0,
    "pct3ResTime" : 7019.0,
    "throughput" : 0.06363938361438608,
    "receivedKBytesPerSec" : 0.16462961640088739,
    "sentKBytesPerSec" : 0.0
  },
  "Total" : {
    "transaction" : "Total",
    "sampleCount" : 1200,
    "errorCount" : 600,
    "errorPct" : 50.0,
    "meanResTime" : 3603.7975000000047,
    "minResTime" : 23.0,
    "maxResTime" : 7020.0,
    "pct1ResTime" : 7016.0,
    "pct2ResTime" : 7017.0,
    "pct3ResTime" : 7019.0,
    "throughput" : 1.3857004946950766,
    "receivedKBytesPerSec" : 13.107861744692189,
    "sentKBytesPerSec" : 0.11389628089534727
  },
  "api/token_trc20/holders" : {
    "transaction" : "api/token_trc20/holders",
    "sampleCount" : 50,
    "errorCount" : 0,
    "errorPct" : 0.0,
    "meanResTime" : 77.28000000000003,
    "minResTime" : 60.0,
    "maxResTime" : 350.0,
    "pct1ResTime" : 88.8,
    "pct2ResTime" : 214.14999999999895,
    "pct3ResTime" : 350.0,
    "throughput" : 0.0641070844739052,
    "receivedKBytesPerSec" : 0.07900697324811365,
    "sentKBytesPerSec" : 0.009202872478187563
  },
  "api/asset/transfer新" : {
    "transaction" : "api/asset/transfer新",
    "sampleCount" : 50,
    "errorCount" : 50,
    "errorPct" : 100.0,
    "meanResTime" : 7014.100000000001,
    "minResTime" : 7009.0,
    "maxResTime" : 7020.0,
    "pct1ResTime" : 7018.9,
    "pct2ResTime" : 7019.45,
    "pct3ResTime" : 7020.0,
    "throughput" : 0.06354685500259907,
    "receivedKBytesPerSec" : 0.16439025283387199,
    "sentKBytesPerSec" : 0.0
  },
  "api/token_trc20" : {
    "transaction" : "api/token_trc20",
    "sampleCount" : 50,
    "errorCount" : 0,
    "errorPct" : 0.0,
    "meanResTime" : 42.34000000000001,
    "minResTime" : 41.0,
    "maxResTime" : 47.0,
    "pct1ResTime" : 43.9,
    "pct2ResTime" : 46.0,
    "pct3ResTime" : 47.0,
    "throughput" : 0.06410938599876653,
    "receivedKBytesPerSec" : 1.7325811993455713,
    "sentKBytesPerSec" : 0.008702348294754442
  },
  "api/tokenholders" : {
    "transaction" : "api/tokenholders",
    "sampleCount" : 50,
    "errorCount" : 0,
    "errorPct" : 0.0,
    "meanResTime" : 77.77999999999999,
    "minResTime" : 69.0,
    "maxResTime" : 115.0,
    "pct1ResTime" : 97.8,
    "pct2ResTime" : 102.24999999999997,
    "pct3ResTime" : 115.0,
    "throughput" : 0.06410667350471184,
    "receivedKBytesPerSec" : 0.089023134495801,
    "sentKBytesPerSec" : 0.011456563722033464
  },
  "api/account" : {
    "transaction" : "api/account",
    "sampleCount" : 50,
    "errorCount" : 0,
    "errorPct" : 0.0,
    "meanResTime" : 23.539999999999996,
    "minResTime" : 23.0,
    "maxResTime" : 25.0,
    "pct1ResTime" : 24.0,
    "pct2ResTime" : 24.0,
    "pct3ResTime" : 25.0,
    "throughput" : 0.06411267417810758,
    "receivedKBytesPerSec" : 0.009704555173444018,
    "sentKBytesPerSec" : 0.008452354505902855
  },
  "api/witness" : {
    "transaction" : "api/witness",
    "sampleCount" : 50,
    "errorCount" : 0,
    "errorPct" : 0.0,
    "meanResTime" : 84.06,
    "minResTime" : 81.0,
    "maxResTime" : 94.0,
    "pct1ResTime" : 89.0,
    "pct2ResTime" : 93.0,
    "pct3ResTime" : 94.0,
    "throughput" : 0.06410782423173184,
    "receivedKBytesPerSec" : 4.456035945978259,
    "sentKBytesPerSec" : 0.008451715108675583
  }
}